crosscompute_table/__init__.py
crosscompute_table/exceptions.py
crosscompute_table/type.jinja2
crosscompute_table/assets/part.min.css
crosscompute_table/assets/part.min.js
crosscompute_table-0.7.7.1.dist-info/DESCRIPTION.rst
crosscompute_table-0.7.7.1.dist-info/METADATA
crosscompute_table-0.7.7.1.dist-info/RECORD
crosscompute_table-0.7.7.1.dist-info/WHEEL
crosscompute_table-0.7.7.1.dist-info/entry_points.txt
crosscompute_table-0.7.7.1.dist-info/metadata.json
crosscompute_table-0.7.7.1.dist-info/top_level.txt
